yta_editor_utils/__init__.py
yta_editor_utils/selection_mask.py
yta_editor_utils/texture.py
yta_editor_utils-0.1.9.dist-info/licenses/LICENSE
yta_editor_utils-0.1.9.dist-info/METADATA
yta_editor_utils-0.1.9.dist-info/WHEEL
yta_editor_utils-0.1.9.dist-info/RECORD
